qv_helper/__init__.py
qv_helper/qv_helper.py
qv_helper-0.1.0.dist-info/LICENSE
qv_helper-0.1.0.dist-info/METADATA
qv_helper-0.1.0.dist-info/WHEEL
qv_helper-0.1.0.dist-info/RECORD
